new_mongo/__init__.py
new_mongo/mongo.py
new_mongo-0.0.9.dist-info/LICENSE
new_mongo-0.0.9.dist-info/METADATA
new_mongo-0.0.9.dist-info/WHEEL
new_mongo-0.0.9.dist-info/top_level.txt
new_mongo-0.0.9.dist-info/RECORD
